{
  "project_info": {
    "project_number": "784298821285",
    "firebase_url": "https://mercate-2022-default-rtdb.firebaseio.com",
    "project_id": "mercate-2022",
    "storage_bucket": "mercate-2022.appspot.com"
  },
  "client": [
    {
      "client_info": {
        "mobilesdk_app_id": "1:784298821285:android:0575fead94df9e828a6f4c",
        "android_client_info": {
          "package_name": "com.example.f_testing_template"
        }
      },
      "oauth_client": [
        {
          "client_id": "784298821285-8vbnf9udns85rq49k1ea96h76ubgpho0.apps.googleusercontent.com",
          "client_type": 3
        }
      ],
      "api_key": [
        {
          "current_key": "AIzaSyDeYn8SFzaA4Df3VglUNIdGvF6SYlHLlaU"
        }
      ],
      "services": {
        "appinvite_service": {
          "other_platform_oauth_client": [
            {
              "client_id": "784298821285-8vbnf9udns85rq49k1ea96h76ubgpho0.apps.googleusercontent.com",
              "client_type": 3
            }
          ]
        }
      }
    }
  ],
  "configuration_version": "1"
}